odoo8_addon_product_warranty-8.0.1.0.0.99.dev35-py3.8-nspkg.pth
odoo_addons/product_warranty/README.rst
odoo_addons/product_warranty/__init__.py
odoo_addons/product_warranty/__openerp__.py
odoo_addons/product_warranty/demo/product_warranty.xml
odoo_addons/product_warranty/demo/res_company.xml
odoo_addons/product_warranty/i18n/am.po
odoo_addons/product_warranty/i18n/ar.po
odoo_addons/product_warranty/i18n/bg.po
odoo_addons/product_warranty/i18n/bs.po
odoo_addons/product_warranty/i18n/ca.po
odoo_addons/product_warranty/i18n/ca_ES.po
odoo_addons/product_warranty/i18n/cs.po
odoo_addons/product_warranty/i18n/da.po
odoo_addons/product_warranty/i18n/de.po
odoo_addons/product_warranty/i18n/el_GR.po
odoo_addons/product_warranty/i18n/en_GB.po
odoo_addons/product_warranty/i18n/es.po
odoo_addons/product_warranty/i18n/es_AR.po
odoo_addons/product_warranty/i18n/es_CL.po
odoo_addons/product_warranty/i18n/es_CO.po
odoo_addons/product_warranty/i18n/es_CR.po
odoo_addons/product_warranty/i18n/es_DO.po
odoo_addons/product_warranty/i18n/es_EC.po
odoo_addons/product_warranty/i18n/es_ES.po
odoo_addons/product_warranty/i18n/es_MX.po
odoo_addons/product_warranty/i18n/es_PA.po
odoo_addons/product_warranty/i18n/es_PE.po
odoo_addons/product_warranty/i18n/es_PY.po
odoo_addons/product_warranty/i18n/es_VE.po
odoo_addons/product_warranty/i18n/et.po
odoo_addons/product_warranty/i18n/eu.po
odoo_addons/product_warranty/i18n/fa.po
odoo_addons/product_warranty/i18n/fi.po
odoo_addons/product_warranty/i18n/fr.po
odoo_addons/product_warranty/i18n/fr_CA.po
odoo_addons/product_warranty/i18n/fr_CH.po
odoo_addons/product_warranty/i18n/fr_FR.po
odoo_addons/product_warranty/i18n/gl.po
odoo_addons/product_warranty/i18n/gl_ES.po
odoo_addons/product_warranty/i18n/he.po
odoo_addons/product_warranty/i18n/hr.po
odoo_addons/product_warranty/i18n/hr_HR.po
odoo_addons/product_warranty/i18n/hu.po
odoo_addons/product_warranty/i18n/id.po
odoo_addons/product_warranty/i18n/it.po
odoo_addons/product_warranty/i18n/ja.po
odoo8_addon_product_warranty-8.0.1.0.0.99.dev35.dist-info/METADATA
odoo8_addon_product_warranty-8.0.1.0.0.99.dev35.dist-info/WHEEL
odoo8_addon_product_warranty-8.0.1.0.0.99.dev35.dist-info/namespace_packages.txt
odoo8_addon_product_warranty-8.0.1.0.0.99.dev35.dist-info/top_level.txt
odoo8_addon_product_warranty-8.0.1.0.0.99.dev35.dist-info/RECORD
